terminal_banner/__init__.py
terminal_banner/_version.py
terminal_banner/banner.py
terminal_banner/bannerbackup.py
terminal_banner/text_box.py
terminal_banner-0.2.0.dist-info/DESCRIPTION.rst
terminal_banner-0.2.0.dist-info/LICENSE.txt
terminal_banner-0.2.0.dist-info/METADATA
terminal_banner-0.2.0.dist-info/RECORD
terminal_banner-0.2.0.dist-info/WHEEL
terminal_banner-0.2.0.dist-info/metadata.json
terminal_banner-0.2.0.dist-info/top_level.txt
